stroomer/__init__.py
stroomer/appliance.py
stroomer/charging.py
stroomer-0.1.6.dist-info/licenses/LICENSE
stroomer-0.1.6.dist-info/METADATA
stroomer-0.1.6.dist-info/WHEEL
stroomer-0.1.6.dist-info/top_level.txt
stroomer-0.1.6.dist-info/RECORD
