Metadata-Version: 2.4
Name: stroomer
Version: 0.1.6
Summary: Energy inference and EV charging ETA utilities (SoC-based).
Author-email: Jauhar Maknun Adib <adibmaknun16@gmail.com>
License: MIT License
Keywords: energy,iot,nilm,ev,charging
Classifier: Programming Language :: Python :: 3
Classifier: License :: OSI Approved :: MIT License
Classifier: Operating System :: OS Independent
Requires-Python: >=3.9
License-File: LICENSE
Dynamic: license-file
